{"General":{"title":"Общие","default":true,"col:0:12":{"fields:0":{"description":{},"pagetitle":{},"longtitle":{},"menutitle":{},"parent":{}}}},"Content":{"title":"Описание","col:0:12":{"fields:0":{"introtext":{"rows":5},"content":{"rows":15},"richtext":{}}}},"tab1648152851440":{"title":"Изображения","col:0:12":{"category:5":{}}},"Seo":{"title":"SEO","col:0:12":{"fields:0":{"metaTitle":{},"metaDescription":{},"metaKeywords":{},"alias":{},"link_attributes":{},"menuindex":{},"hidemenu":{}}}},"Settings":{"title":"Настройка страницы","col:0:12":{"fields:0":{"template":{},"weblink":{},"published":{},"alias_visible":{},"isfolder":{},"donthit":{},"contentType":{},"type":{},"content_dispo":{},"pub_date":{},"unpub_date":{},"createdon":{},"editedon":{},"searchable":{},"cacheable":{},"syncsite":{}}}},"#Static":{"title":"Static","col:0:12":{}}}